animag/Searcher.py
animag/__init__.py
animag/cli.py
animag/component/Anime.py
animag/component/__init__.py
animag/component/errors.py
animag/component/webget.py
animag/plugins/__init__.py
animag/plugins/_miobt.py
animag/plugins/acgrip.py
animag/plugins/acgrip_rss.py
animag/plugins/animetosho.py
animag/plugins/animetosho_rss.py
animag/plugins/dmhy.py
animag/plugins/dmhy_rss.py
animag/plugins/nyaa.py
animag/plugins/nyaa_rss.py
animag/plugins/tokyotosho.py
animag/plugins/tokyotosho_rss.py
animag-2.1.1.dist-info/LICENSE
animag-2.1.1.dist-info/METADATA
animag-2.1.1.dist-info/WHEEL
animag-2.1.1.dist-info/entry_points.txt
animag-2.1.1.dist-info/top_level.txt
animag-2.1.1.dist-info/RECORD
