Metadata-Version: 2.1
Name: animag
Version: 2.1.1
Summary: Anime magnet search library with strong scalability.
Home-page: https://github.com/adogecheems/animag
Author: adogecheems
Author-email: master@mmoe.work
License: AGPLv3
Keywords: plugin rss torrent scraper scalable scalability magnet-link torrents magnet animes nyaa-magnet-links nyaa anime-scraper dmhy nyaa-si animetosho tokyotoshokan acgrip dmhy-org acg-rip
Classifier: Development Status :: 5 - Production/Stable
Classifier: License :: OSI Approved :: GNU Affero General Public License v3
Classifier: Programming Language :: Python :: 3
Classifier: Programming Language :: Python :: 3.8
Classifier: Programming Language :: Python :: 3.9
Classifier: Programming Language :: Python :: 3.10
Classifier: Programming Language :: Python :: 3.11
Classifier: Programming Language :: Python :: 3.12
License-File: LICENSE
Requires-Dist: requests
Requires-Dist: bs4
Requires-Dist: lxml
Requires-Dist: rich
